NiukeDichanXingyeMingqiBiMianshiXiaozhaoQiuzhiGonglve20212022Fix1/README.md
NiukeDichanXingyeMingqiBiMianshiXiaozhaoQiuzhiGonglve20212022Fix1/__init__.py
NiukeDichanXingyeMingqiBiMianshiXiaozhaoQiuzhiGonglve20212022Fix1/__main__.py
NiukeDichanXingyeMingqiBiMianshiXiaozhaoQiuzhiGonglve20212022Fix1/file.epub
NiukeDichanXingyeMingqiBiMianshiXiaozhaoQiuzhiGonglve20212022Fix1/index.html
NiukeDichanXingyeMingqiBiMianshiXiaozhaoQiuzhiGonglve20212022Fix1/css/__init__.py
NiukeDichanXingyeMingqiBiMianshiXiaozhaoQiuzhiGonglve20212022Fix1/css/annotations.css
NiukeDichanXingyeMingqiBiMianshiXiaozhaoQiuzhiGonglve20212022Fix1/css/main.css
NiukeDichanXingyeMingqiBiMianshiXiaozhaoQiuzhiGonglve20212022Fix1/css/normalize.css
NiukeDichanXingyeMingqiBiMianshiXiaozhaoQiuzhiGonglve20212022Fix1/css/popup.css
NiukeDichanXingyeMingqiBiMianshiXiaozhaoQiuzhiGonglve20212022Fix1/font/__init__.py
NiukeDichanXingyeMingqiBiMianshiXiaozhaoQiuzhiGonglve20212022Fix1/font/fontello.eot
NiukeDichanXingyeMingqiBiMianshiXiaozhaoQiuzhiGonglve20212022Fix1/font/fontello.svg
NiukeDichanXingyeMingqiBiMianshiXiaozhaoQiuzhiGonglve20212022Fix1/font/fontello.ttf
NiukeDichanXingyeMingqiBiMianshiXiaozhaoQiuzhiGonglve20212022Fix1/font/fontello.woff
NiukeDichanXingyeMingqiBiMianshiXiaozhaoQiuzhiGonglve20212022Fix1/img/__init__.py
NiukeDichanXingyeMingqiBiMianshiXiaozhaoQiuzhiGonglve20212022Fix1/img/annotator-glyph-sprite.png
NiukeDichanXingyeMingqiBiMianshiXiaozhaoQiuzhiGonglve20212022Fix1/img/annotator-icon-sprite.png
NiukeDichanXingyeMingqiBiMianshiXiaozhaoQiuzhiGonglve20212022Fix1/img/apple-touch-icon.png
NiukeDichanXingyeMingqiBiMianshiXiaozhaoQiuzhiGonglve20212022Fix1/img/cancelfullscreen.png
NiukeDichanXingyeMingqiBiMianshiXiaozhaoQiuzhiGonglve20212022Fix1/img/close.png
NiukeDichanXingyeMingqiBiMianshiXiaozhaoQiuzhiGonglve20212022Fix1/img/fullscreen.png
NiukeDichanXingyeMingqiBiMianshiXiaozhaoQiuzhiGonglve20212022Fix1/img/loader.gif
niuke_dichan_xingye_mingqi_bi_mianshi_xiaozhao_qiuzhi_gonglve_2021_2022_fix1-2025.3.25.1.dist-info/METADATA
niuke_dichan_xingye_mingqi_bi_mianshi_xiaozhao_qiuzhi_gonglve_2021_2022_fix1-2025.3.25.1.dist-info/WHEEL
niuke_dichan_xingye_mingqi_bi_mianshi_xiaozhao_qiuzhi_gonglve_2021_2022_fix1-2025.3.25.1.dist-info/entry_points.txt
niuke_dichan_xingye_mingqi_bi_mianshi_xiaozhao_qiuzhi_gonglve_2021_2022_fix1-2025.3.25.1.dist-info/top_level.txt
niuke_dichan_xingye_mingqi_bi_mianshi_xiaozhao_qiuzhi_gonglve_2021_2022_fix1-2025.3.25.1.dist-info/RECORD
